LeshanRestAPI/__init__.py
LeshanRestAPI/runner.py
LeshanRestAPI/cached_clients/358185090000024.json
LeshanRestAPI/cached_clients/US-L15-0253.json
LeshanRestAPI/cached_clients/dhkimlwm2mclient.json
LeshanRestAPI/cached_clients/ezhiand-test-virtualdev-leshan.json
LeshanRestAPI/cached_clients/hexa_test.json
LeshanRestAPI-0.1.2.dist-info/METADATA
LeshanRestAPI-0.1.2.dist-info/RECORD
LeshanRestAPI-0.1.2.dist-info/WHEEL
LeshanRestAPI-0.1.2.dist-info/top_level.txt
